txtanim/__init__.py
txtanim/txtanim.py
txtanim-1.0.2.dist-info/licenses/LICENCE
txtanim-1.0.2.dist-info/METADATA
txtanim-1.0.2.dist-info/WHEEL
txtanim-1.0.2.dist-info/top_level.txt
txtanim-1.0.2.dist-info/RECORD
