Metadata-Version: 2.4
Name: txtanim
Version: 1.0.2
Summary: Terminal text animations for Python.
Author: Neunix Studios
Requires-Python: >=3.6
License-File: LICENCE
Requires-Dist: pyfiglet>=0.8.post1
Dynamic: author
Dynamic: license-file
Dynamic: requires-python
